[
  {
    "id": "001",
    "title": "Latebloomers at Boomerang",
    "slug": "latebloomers-at-boomerang-2026-08-08",
    "date": "2026-08-08",
    "startTime": "23:00",
    "endTime": "06:00",
    "venue": "Boomerang",
    "locationLabel": "The Hague, NL",
    "type": "club night",
    "status": "upcoming",
    "description": "Latebloomers returns to Boomerang for a night of deep, percussive, and hypnotic sounds.",
    "lineup": [
      { "name": "Giammarco Orsini", "order": 1 },
      { "name": "DJ Tjizza", "order": 2 },
      { "name": "Roy Koch", "order": 3 },
      { "name": "DJ Z", "order": 4 }
    ],
    "artwork": "/images/events/Event1.png",
    "ticketUrl": null,
    "instagramUrl": null,
    "featured": true,
    "seo": {
      "title": "Latebloomers at Boomerang — 8 August 2026",
      "description": "Latebloomers presents a night at Boomerang, The Hague featuring Giammarco Orsini, DJ Tjizza, Roy Koch and DJ Z."
    }
  }
]
